coininfo-saeideh/__init__.py
coininfo-saeideh/info.py
tests/__init__.py
tests/test_project.py
coininfo_saeideh-1.1.3.dist-info/METADATA
coininfo_saeideh-1.1.3.dist-info/WHEEL
coininfo_saeideh-1.1.3.dist-info/top_level.txt
coininfo_saeideh-1.1.3.dist-info/RECORD
