Metadata-Version: 2.1
Name: coininfo-saeideh
Version: 1.1.3
Requires-Dist: requests ==2.31.0
